<biblioteca>
	
  <libro id="1">
	  <titulo>Callejon sin salida</titulo>
	  <editorial>Acantilado</editorial>
	  <paginas>158</paginas>
	  <altura>4</altura>
	  <notas>10</notas>
	  <isbn>978-987-1565-25-2</isbn>
	  <materias>a</materias>
  </libro>

	<libro id="2">
		<titulo>El Gigante Amapolas</titulo>
		<editorial>Alba</editorial>
		<paginas>250</paginas>
		<altura>25</altura>
		<notas>5</notas>
		<isbn>978-987-1565-26-9</isbn>
		<materias>b</materias>
	</libro>


</biblioteca>